beward/__init__.py
beward/camera.py
beward/const.py
beward/core.py
beward/doorbell.py
beward/util.py
beward-1.1.14.dist-info/LICENSE.md
beward-1.1.14.dist-info/METADATA
beward-1.1.14.dist-info/WHEEL
beward-1.1.14.dist-info/top_level.txt
beward-1.1.14.dist-info/RECORD
