Metadata-Version: 2.2
Name: beward
Version: 1.1.14
Summary: Beward Client
Author-email: "Andrey \"Limych\" Khrolenok" <andrey@khrolenok.ru>
License: # MIT License
Project-URL: Homepage, https://github.com/Limych/py-beward
Project-URL: Documentation, https://github.com/Limych/py-beward/README.md
Project-URL: Issues, https://github.com/Limych/py-beward/issues
Project-URL: New Device, https://github.com/Limych/py-beward/issues/new?template=new_device.yml
Keywords: beward
Classifier: Development Status :: 5 - Production/Stable
Classifier: Intended Audience :: Developers
Classifier: Topic :: Home Automation
Classifier: Topic :: Security
Classifier: Topic :: Multimedia :: Video :: Capture
Classifier: License :: Other/Proprietary License
Classifier: Operating System :: OS Independent
Classifier: Programming Language :: Python :: 3
Classifier: Programming Language :: Python :: 3.10
Classifier: Programming Language :: Python :: 3.11
Classifier: Programming Language :: Python :: 3.12
Classifier: Programming Language :: Python :: Implementation :: CPython
Requires-Python: >=3.10
License-File: LICENSE.md
Requires-Dist: requests~=2.31
Requires-Dist: hexdump==3.3
Requires-Dist: urllib3
Dynamic: requires-dist
